randominfo/__init__.py
randominfo/data.csv
randominfo/images/people/female_1.jpg
randominfo/images/people/female_10.jpg
randominfo/images/people/female_11.jpg
randominfo/images/people/female_12.jpg
randominfo/images/people/female_13.jpg
randominfo/images/people/female_14.jpg
randominfo/images/people/female_15.jpg
randominfo/images/people/female_16.jpg
randominfo/images/people/female_17.jpg
randominfo/images/people/female_18.jpg
randominfo/images/people/female_19.jpg
randominfo/images/people/female_2.jpg
randominfo/images/people/female_20.jpg
randominfo/images/people/female_21.jpg
randominfo/images/people/female_22.jpg
randominfo/images/people/female_23.jpg
randominfo/images/people/female_24.jpg
randominfo/images/people/female_25.jpg
randominfo/images/people/female_26.jpg
randominfo/images/people/female_27.jpg
randominfo/images/people/female_28.jpg
randominfo/images/people/female_29.jpg
randominfo/images/people/female_3.jpg
randominfo/images/people/female_30.jpg
randominfo/images/people/female_31.jpg
randominfo/images/people/female_32.jpg
randominfo/images/people/female_33.jpg
randominfo/images/people/female_34.jpg
randominfo/images/people/female_35.jpg
randominfo/images/people/female_36.jpg
randominfo/images/people/female_37.jpg
randominfo/images/people/female_38.jpg
randominfo/images/people/female_39.jpg
randominfo/images/people/female_4.jpg
randominfo/images/people/female_40.jpg
randominfo/images/people/female_42.jpg
randominfo/images/people/female_43.jpg
randominfo/images/people/female_44.jpg
randominfo/images/people/female_45.jpg
randominfo/images/people/female_46.jpg
randominfo/images/people/female_47.jpg
randominfo/images/people/female_48.jpg
randominfo/images/people/female_49.jpg
randominfo/images/people/female_5.jpg
randominfo/images/people/female_50.jpg
randominfo/images/people/female_51.jpg
randominfo/images/people/female_52.jpg
randominfo/images/people/female_53.jpg
randominfo/images/people/female_54.jpg
randominfo/images/people/female_55.jpg
randominfo-2.0.2.dist-info/LICENSE
randominfo-2.0.2.dist-info/METADATA
randominfo-2.0.2.dist-info/WHEEL
randominfo-2.0.2.dist-info/top_level.txt
randominfo-2.0.2.dist-info/RECORD
