Metadata-Version: 2.1
Name: randominfo
Version: 2.0.2
Summary: Random data generator for IDs, names, emails, passwords, dates, numbers, addresses, images, OTPs etc. for dummy entries.
Home-page: https://github.com/bmg02/randominfo
Author: Bhuvan Gandhi
Author-email: bhuvan12501@gmail.com
License: UNKNOWN
Download-URL: https://github.com/bmg02/randominfo/dist/randominfo-2.0.2.tar.gz
Platform: UNKNOWN
Classifier: Programming Language :: Python :: 3
Classifier: License :: OSI Approved :: MIT License
Classifier: Operating System :: OS Independent
Requires-Python: >=3
Requires-Dist: pillow (>=5.4.1)
Requires-Dist: pytz (>=2018.5)
